MQTTSimpleClient/MqttPubSub.py
MQTTSimpleClient/__init__.py
MQTTSimpleClient/configuration.py
MQTTSimpleClient/my_logger.py
MQTTSimpleClient/cfg/conf.xml
MQTTSimpleClient-0.2.0.dist-info/METADATA
MQTTSimpleClient-0.2.0.dist-info/WHEEL
MQTTSimpleClient-0.2.0.dist-info/top_level.txt
MQTTSimpleClient-0.2.0.dist-info/RECORD
